phonexia_speech_to_text_client.py
phonexia_speech_to_text_client-2.1.1.dist-info/METADATA
phonexia_speech_to_text_client-2.1.1.dist-info/WHEEL
phonexia_speech_to_text_client-2.1.1.dist-info/entry_points.txt
phonexia_speech_to_text_client-2.1.1.dist-info/top_level.txt
phonexia_speech_to_text_client-2.1.1.dist-info/RECORD
