Metadata-Version: 2.4
Name: phonexia-speech-to-text-client
Version: 2.1.1
Summary: Client for communication with Phonexia speech to text microservice.
Author-email: Phonexia <info@phonexia.com>
Keywords: speech-to-text,audio,voice,speech,search,grpc
Requires-Python: >=3.9
Requires-Dist: grpcio-status>=1.48.0
Requires-Dist: more-itertools>=10.6.0
Requires-Dist: phonexia-grpc>=2.27.1
Requires-Dist: numpy>=2.0.0; python_version >= "3.12"
Requires-Dist: numpy<2.0.0; python_version < "3.12"
Requires-Dist: typer>=0.16.0
Requires-Dist: soundfile>=0.13.0
